{ "height":15,
 "layers":[
        {
         "data":[4, 4, 4, 4, 4, 4, 4, 4, 4, 4, 4, 4, 4, 4, 4, 4, 4, 4, 4, 4, 4, 4, 4, 4, 4, 4, 4, 4, 4, 4, 4, 4, 4, 4, 4, 4, 4, 4, 4, 4, 4, 4, 4, 4, 4, 4, 4, 4, 4, 4, 4, 4, 4, 4, 4, 4, 4, 4, 4, 4, 4, 4, 4, 4, 4, 4, 4, 4, 4, 4, 4, 4, 4, 4, 4, 4, 4, 4, 4, 4, 4, 4, 4, 4, 4, 4, 4, 4, 4, 4, 4, 4, 4, 4, 4, 4, 4, 4, 4, 4, 4, 4, 4, 4, 4, 4, 4, 4, 4, 4, 4, 4, 4, 4, 4, 4, 4, 4, 4, 4, 4, 4, 4, 4, 4, 4, 4, 4, 4, 4, 4, 4, 4, 4, 4, 4, 4, 4, 4, 4, 4, 4, 4, 4, 4, 4, 4, 4, 4, 4, 4, 4, 4, 4, 1, 1, 1, 1, 1, 1, 1, 4, 4, 4, 4, 4, 4, 4, 4, 4, 1, 1, 1, 1, 1, 4, 4, 4, 4, 4, 4, 4, 4, 4, 4, 4, 4, 4, 4, 4, 4, 4, 4, 4, 4, 1, 1, 1, 1, 1, 1, 1, 1, 1, 1, 1, 4, 4, 4, 4, 4, 4, 4, 4, 4, 4, 4, 4, 4, 4, 4, 4, 4, 4, 4, 4, 4, 4, 4, 4, 4, 4, 4, 4, 4, 4, 4, 4, 4, 4, 4, 4, 4, 4, 4, 4, 4, 4, 4, 4, 4, 4, 4, 4, 4, 4, 4, 4, 4, 4, 4, 4, 4, 4, 4, 4, 4, 4, 4, 4, 4, 4, 4, 4, 4, 4, 4, 4, 4, 4, 4, 4, 4, 4, 4, 4, 4, 4, 4, 4, 4, 4, 4, 4, 4, 4, 4, 4, 4, 4, 4, 4, 4, 4, 4, 4, 4, 4, 4, 4, 4, 4, 4, 4, 4, 4, 4, 4, 4, 4, 4, 4, 4, 4, 4, 4, 4, 4, 4, 4, 4, 4, 4, 4, 4, 4, 4, 4, 4, 1, 1, 1, 1, 1, 1, 1, 1, 1, 1, 1, 4, 4, 4, 4, 4, 4, 4, 4, 4, 4, 4, 4, 4, 4, 4, 4, 4, 4, 4, 4, 4, 4, 4, 4, 4, 4, 4, 4, 4, 4, 4, 4, 4, 4, 4, 4, 4, 4, 4, 4, 4, 4, 4, 4, 4, 1, 1, 1, 1, 1, 1, 1, 1, 4, 4, 4, 4, 4, 4, 4, 4, 4, 4, 4, 4, 4, 4, 4, 4, 4, 4, 4, 4, 4, 4, 4, 4, 4, 4, 4, 4, 4, 4, 4, 4, 4, 4, 1, 4, 4, 4, 4, 4, 4, 4, 4, 4, 4, 4, 4, 4, 4, 4, 4, 4, 4, 4, 4, 4, 4, 4, 4, 4, 4, 4, 4, 4, 4, 4, 4, 4, 4, 1, 4, 4, 4, 4, 4, 4, 4, 4, 4, 4, 4, 4, 4, 4, 4, 4, 4, 1, 1, 1, 1, 1, 1, 1, 1, 1, 1, 1, 4, 4, 4, 4, 4, 4, 1, 1, 1, 1, 1, 1, 1, 1, 1, 1, 1, 1, 1, 1, 1, 1, 1, 1],
         "height":15,
         "name":"tileLayer",
         "opacity":1,
         "type":"tilelayer",
         "visible":true,
         "width":35,
         "x":0,
         "y":0
        }, 
        {
         "draworder":"topdown",
         "name":"objectLayer",
         "objects":[
                {
                 "height":55.8996,
                 "id":1,
                 "name":"playerSpawn",
                 "rotation":0,
                 "type":"playerSpawn",
                 "visible":true,
                 "width":28.3798,
                 "x":57.3059,
                 "y":382.806
                }, 
                {
                 "height":55.8996,
                 "id":23,
                 "name":"enemy1",
                 "rotation":0,
                 "type":"spawn",
                 "visible":true,
                 "width":28.3798,
                 "x":599.833,
                 "y":60.558
                }, 
                {
                 "height":55.8996,
                 "id":24,
                 "name":"enemy2",
                 "rotation":0,
                 "type":"enemySpawn",
                 "visible":true,
                 "width":28.3798,
                 "x":1010.56,
                 "y":63.3239
                }, 
                {
                 "height":55.8996,
                 "id":25,
                 "name":"enemy3",
                 "rotation":0,
                 "type":"enemySpawn",
                 "visible":true,
                 "width":28.3798,
                 "x":880.569,
                 "y":222.361
                }, 
                {
                 "height":55.8996,
                 "id":26,
                 "name":"enemy4",
                 "rotation":0,
                 "type":"enemySpawn",
                 "visible":true,
                 "width":28.3798,
                 "x":720.148,
                 "y":380.016
                }],
         "opacity":1,
         "type":"objectgroup",
         "visible":true,
         "x":0,
         "y":0
        }],
 "nextobjectid":27,
 "orientation":"orthogonal",
 "renderorder":"right-down",
 "tiledversion":"1.0.3",
 "tileheight":32,
 "tilesets":[
        {
         "columns":2,
         "firstgid":1,
         "image":"tiles.png",
         "imageheight":64,
         "imagewidth":64,
         "margin":0,
         "name":"tiles",
         "spacing":0,
         "tilecount":4,
         "tileheight":32,
         "tiles":
            {
             "0":
                {
                 "objectgroup":
                    {
                     "draworder":"index",
                     "name":"",
                     "objects":[],
                     "opacity":1,
                     "properties":
                        {
                         "solid":true
                        },
                     "propertytypes":
                        {
                         "solid":"bool"
                        },
                     "type":"objectgroup",
                     "visible":true,
                     "x":0,
                     "y":0
                    }
                }
            },
         "tilewidth":32
        }],
 "tilewidth":32,
 "type":"map",
 "version":1,
 "width":35
}